<author type="review" lang="EN" gender="xx" age_group="xx" url="">
	<documents count="4">
		<document id="01549726796568fd97810e62c6690d8d" url=""><![CDATA[Impressive hotel in excellent location View from one of our rooms
]]>
		</document>
		<document id="f9d67ebbdda5e2be9c179cb5b16b32e4" url=""><![CDATA[Brilliant hotel in very good location Lobby Bar
]]>
		</document>
		<document id="a55f27fe9521c46af61d3f4c3711b1a5" url=""><![CDATA[Excellent stay in the Langham Place Hotel Mongkok! Beds
]]>
		</document>
		<document id="e3a22c20fe463eaf87f87b24ab92b583" url=""><![CDATA[Good hotel, excellent location, amazing views! Hotel exterior (silver tower in background)
]]>
		</document>
	</documents>
</author>